productspy/__init__.py
productspy/exceptions.py
productspy/trackers/__init__.py
productspy/trackers/aliexpress.py
productspy/trackers/amazon.py
productspy/trackers/carrefour.py
productspy/trackers/extra.py
productspy/trackers/noon.py
productspy/utils/__init__.py
productspy/utils/cookies_manager.py
productspy/utils/url_tools.py
productspy-0.1.6.dist-info/METADATA
productspy-0.1.6.dist-info/WHEEL
productspy-0.1.6.dist-info/top_level.txt
productspy-0.1.6.dist-info/RECORD
