Metadata-Version: 2.4
Name: productspy
Version: 0.1.6
Summary: A simple Python library to fetch product name and price from popular e-commerce websites.
Author-email: Rayan <xrayan.23@gmail.com>
License: MIT
Project-URL: Homepage, https://pypi.org/project/productspy/
Project-URL: Repository, https://github.com/Renqwee/productspy
Requires-Python: >=3.8
Requires-Dist: requests>=2.31.0
Requires-Dist: beautifulsoup4>=4.12.0
Requires-Dist: urllib3>=1.26.0
Requires-Dist: playwright>=1.40.0
